refs/__init__.py
refs/_utils.py
refs/admin.py
refs/apps.py
refs/export_utils.py
refs/filters.py
refs/forms.py
refs/models.py
refs/urls.py
refs/views.py
refs/xsams_generators.py
refs/xsams_settings.py
refs/xsams_utils.py
refs/migrations/0001_initial.py
refs/migrations/__init__.py
refs/templatetags/__init__.py
refs/templatetags/pyref_tags.py
django_ref-0.5.2.dist-info/LICENSE
django_ref-0.5.2.dist-info/METADATA
django_ref-0.5.2.dist-info/WHEEL
django_ref-0.5.2.dist-info/top_level.txt
django_ref-0.5.2.dist-info/RECORD
