Metadata-Version: 2.1
Name: django-ref
Version: 0.5.2
Summary: A Django app defining data models for managing bibliographic references for scientific databases.
Home-page: https://github.com/xnx/django-valem
Author: Christian Hill, Frances Skinner, Iouli Gordon, Robert Hargreaves, Kelly Lockhart
Author-email: ch.hill@iaea.org
Project-URL: Bug Reports, https://github.com/xnx/django-pyref/issues
Keywords: django,database,references,citation
Classifier: Development Status :: 3 - Alpha
Classifier: Intended Audience :: Science/Research
Classifier: Topic :: Scientific/Engineering :: Chemistry
Classifier: Topic :: Scientific/Engineering :: Physics
Classifier: License :: OSI Approved :: Apache Software License
Classifier: Programming Language :: Python :: 3
Classifier: Programming Language :: Python :: 3.6
Classifier: Programming Language :: Python :: 3.7
Classifier: Programming Language :: Python :: 3.8
Classifier: Programming Language :: Python :: 3.9
Classifier: Programming Language :: Python :: 3.10
Classifier: Programming Language :: Python :: 3 :: Only
Classifier: Framework :: Django
Classifier: Operating System :: OS Independent
Requires-Python: >=3.6
License-File: LICENSE
Requires-Dist: Django (>=3.2)
Requires-Dist: requests (>=2.28.1)
Provides-Extra: dev
Requires-Dist: black ; extra == 'dev'
Requires-Dist: coverage ; extra == 'dev'
Requires-Dist: ipython ; extra == 'dev'
